{
  "meta": {
    "season": "درع إحسان 2026",
    "seasonYear": 2026,
    "generatedAt": "2026-07-20T03:48:00Z",
    "sourceFile": "Google Sheets",
    "programDays": 11,
    "scoringDays": 10,
    "completedDays": 1,
    "totalWeeks": 4,
    "completedWeeks": 1,
    "completionPct": 10,
    "comment": "حفل ختامي - يوم 11"
  },
  "weights": [
    {
      "nameAr": "الدوري التنافسي",
      "weightPct": 30,
      "note": "كرة قدم (10٪) + طائرة (10٪) + ثقافي (10٪)"
    },
    {
      "nameAr": "المشروع المجتمعي",
      "weightPct": 20,
      "note": "خمسة معايير تقييم"
    },
    {
      "nameAr": "البرنامج الحركي",
      "weightPct": 10,
      "note": "برنامجان × ٥٪ حسب الترتيب"
    },
    {
      "nameAr": "الزي الموحد",
      "weightPct": 10,
      "note": "نسبة الالتزام × ١٪ لكل برنامج"
    },
    {
      "nameAr": "الحضور",
      "weightPct": 10,
      "note": "نسبة الحضور × ١٪ لكل برنامج"
    },
    {
      "nameAr": "الخواطر التربوية",
      "weightPct": 5,
      "note": "اللجنة التربوية"
    },
    {
      "nameAr": "وسام محسن",
      "weightPct": 4,
      "note": "تقييم أسبوعي — ١٪ أسبوعياً"
    },
    {
      "nameAr": "فقرة مبكرون",
      "weightPct": 4,
      "note": "أول ١٥ دقيقة — مسابقة مستقلة"
    },
    {
      "nameAr": "الورش التدريبية",
      "weightPct": 3,
      "note": "اللجنة التربوية"
    },
    {
      "nameAr": "الظهور الإعلامي",
      "weightPct": 2,
      "note": "اللجنة الإعلامية"
    },
    {
      "nameAr": "الصورة الجماعية",
      "weightPct": 2,
      "note": "مرتان × ١٪"
    }
  ],
  "groups": [
    {
      "id": "G01",
      "index": 0,
      "nameAr": "أبو بكر الصديق",
      "captain": "أسامة بن غيث",
      "deputy": "النائب 1",
      "members": 11,
      "rank": 1,
      "totalPct": 54.236,
      "medal": 1,
      "movement": null,
      "categories": [
        {
          "id": "football",
          "nameAr": "كرة القدم",
          "scorePct": 10,
          "maxPct": 10,
          "pct": 100
        },
        {
          "id": "volleyball",
          "nameAr": "كرة الطائرة",
          "scorePct": 15,
          "maxPct": 10,
          "pct": 150
        },
        {
          "id": "cultural",
          "nameAr": "المسابقة الثقافية",
          "scorePct": 9,
          "maxPct": 10,
          "pct": 90
        },
        {
          "id": "community",
          "nameAr": "اترك أثراً",
          "scorePct": 0,
          "maxPct": 20,
          "pct": 0
        },
        {
          "id": "haraki",
          "nameAr": "البرنامج الحركي",
          "scorePct": 5,
          "maxPct": 10,
          "pct": 50
        },
        {
          "id": "attendance",
          "nameAr": "الحضور",
          "scorePct": 0.909,
          "maxPct": 10,
          "pct": 9.09
        },
        {
          "id": "uniform",
          "nameAr": "الزي الموحد",
          "scorePct": 0.727,
          "maxPct": 10,
          "pct": 7.27
        },
        {
          "id": "reflections",
          "nameAr": "الخواطر التربوية",
          "scorePct": 3.5,
          "maxPct": 5,
          "pct": 70
        },
        {
          "id": "mohsen",
          "nameAr": "وسام محسن",
          "scorePct": 4,
          "maxPct": 4,
          "pct": 100
        },
        {
          "id": "mubakkirun",
          "nameAr": "فقرة مبكرون",
          "scorePct": 1,
          "maxPct": 4,
          "pct": 25
        },
        {
          "id": "workshops",
          "nameAr": "الورش التدريبية",
          "scorePct": 2.1,
          "maxPct": 3,
          "pct": 70
        },
        {
          "id": "media",
          "nameAr": "الظهور الإعلامي",
          "scorePct": 2,
          "maxPct": 2,
          "pct": 100
        },
        {
          "id": "groupPhoto",
          "nameAr": "الصورة الجماعية",
          "scorePct": 1,
          "maxPct": 2,
          "pct": 50
        }
      ],
      "components": [
        {
          "id": "league",
          "nameAr": "الدوري التنافسي",
          "scorePct": 34,
          "maxPct": 30,
          "pct": 113.333
        },
        {
          "id": "project",
          "nameAr": "المشروع المجتمعي",
          "scorePct": 0,
          "maxPct": 20,
          "pct": 0
        },
        {
          "id": "haraki",
          "nameAr": "البرنامج الحركي",
          "scorePct": 5,
          "maxPct": 10,
          "pct": 50
        },
        {
          "id": "uniform",
          "nameAr": "الزي الموحد",
          "scorePct": 0.727,
          "maxPct": 10,
          "pct": 7.27
        },
        {
          "id": "attendance",
          "nameAr": "الحضور",
          "scorePct": 0.909,
          "maxPct": 10,
          "pct": 9.09
        },
        {
          "id": "educational",
          "nameAr": "الخواطر والورش",
          "scorePct": 5.6,
          "maxPct": 8,
          "pct": 70
        },
        {
          "id": "mohsen",
          "nameAr": "وسام محسن",
          "scorePct": 4,
          "maxPct": 4,
          "pct": 100
        },
        {
          "id": "mubakkirun",
          "nameAr": "فقرة مبكرون",
          "scorePct": 1,
          "maxPct": 4,
          "pct": 25
        },
        {
          "id": "mediaPhoto",
          "nameAr": "الإعلام والصورة",
          "scorePct": 3,
          "maxPct": 4,
          "pct": 75
        }
      ]
    },
    {
      "id": "G02",
      "index": 1,
      "nameAr": "عمر بن الخطاب",
      "captain": "غانم الغانم",
      "deputy": "النائب 2",
      "members": 12,
      "rank": 6,
      "totalPct": 25.6,
      "medal": null,
      "movement": null,
      "categories": [
        {
          "id": "football",
          "nameAr": "كرة القدم",
          "scorePct": 1.667,
          "maxPct": 10,
          "pct": 16.67
        },
        {
          "id": "volleyball",
          "nameAr": "كرة الطائرة",
          "scorePct": 1.667,
          "maxPct": 10,
          "pct": 16.67
        },
        {
          "id": "cultural",
          "nameAr": "المسابقة الثقافية",
          "scorePct": 4,
          "maxPct": 10,
          "pct": 40
        },
        {
          "id": "community",
          "nameAr": "اترك أثراً",
          "scorePct": 0,
          "maxPct": 20,
          "pct": 0
        },
        {
          "id": "haraki",
          "nameAr": "البرنامج الحركي",
          "scorePct": 4.5,
          "maxPct": 10,
          "pct": 45
        },
        {
          "id": "attendance",
          "nameAr": "الحضور",
          "scorePct": 0.667,
          "maxPct": 10,
          "pct": 6.67
        },
        {
          "id": "uniform",
          "nameAr": "الزي الموحد",
          "scorePct": 0.5,
          "maxPct": 10,
          "pct": 5
        },
        {
          "id": "reflections",
          "nameAr": "الخواطر التربوية",
          "scorePct": 3.5,
          "maxPct": 5,
          "pct": 70
        },
        {
          "id": "mohsen",
          "nameAr": "وسام محسن",
          "scorePct": 3,
          "maxPct": 4,
          "pct": 75
        },
        {
          "id": "mubakkirun",
          "nameAr": "فقرة مبكرون",
          "scorePct": 1,
          "maxPct": 4,
          "pct": 25
        },
        {
          "id": "workshops",
          "nameAr": "الورش التدريبية",
          "scorePct": 2.1,
          "maxPct": 3,
          "pct": 70
        },
        {
          "id": "media",
          "nameAr": "الظهور الإعلامي",
          "scorePct": 1,
          "maxPct": 2,
          "pct": 50
        },
        {
          "id": "groupPhoto",
          "nameAr": "الصورة الجماعية",
          "scorePct": 2,
          "maxPct": 2,
          "pct": 100
        }
      ],
      "components": [
        {
          "id": "league",
          "nameAr": "الدوري التنافسي",
          "scorePct": 7.333,
          "maxPct": 30,
          "pct": 24.443
        },
        {
          "id": "project",
          "nameAr": "المشروع المجتمعي",
          "scorePct": 0,
          "maxPct": 20,
          "pct": 0
        },
        {
          "id": "haraki",
          "nameAr": "البرنامج الحركي",
          "scorePct": 4.5,
          "maxPct": 10,
          "pct": 45
        },
        {
          "id": "uniform",
          "nameAr": "الزي الموحد",
          "scorePct": 0.5,
          "maxPct": 10,
          "pct": 5
        },
        {
          "id": "attendance",
          "nameAr": "الحضور",
          "scorePct": 0.667,
          "maxPct": 10,
          "pct": 6.67
        },
        {
          "id": "educational",
          "nameAr": "الخواطر والورش",
          "scorePct": 5.6,
          "maxPct": 8,
          "pct": 70
        },
        {
          "id": "mohsen",
          "nameAr": "وسام محسن",
          "scorePct": 3,
          "maxPct": 4,
          "pct": 75
        },
        {
          "id": "mubakkirun",
          "nameAr": "فقرة مبكرون",
          "scorePct": 1,
          "maxPct": 4,
          "pct": 25
        },
        {
          "id": "mediaPhoto",
          "nameAr": "الإعلام والصورة",
          "scorePct": 3,
          "maxPct": 4,
          "pct": 75
        }
      ]
    },
    {
      "id": "G03",
      "index": 2,
      "nameAr": "عثمان بن عفان",
      "captain": "اوس الحداد",
      "deputy": "النائب 3",
      "members": 11,
      "rank": 4,
      "totalPct": 32.697,
      "medal": null,
      "movement": null,
      "categories": [
        {
          "id": "football",
          "nameAr": "كرة القدم",
          "scorePct": 4.167,
          "maxPct": 10,
          "pct": 41.67
        },
        {
          "id": "volleyball",
          "nameAr": "كرة الطائرة",
          "scorePct": 4.167,
          "maxPct": 10,
          "pct": 41.67
        },
        {
          "id": "cultural",
          "nameAr": "المسابقة الثقافية",
          "scorePct": 3,
          "maxPct": 10,
          "pct": 30
        },
        {
          "id": "community",
          "nameAr": "اترك أثراً",
          "scorePct": 0,
          "maxPct": 20,
          "pct": 0
        },
        {
          "id": "haraki",
          "nameAr": "البرنامج الحركي",
          "scorePct": 4,
          "maxPct": 10,
          "pct": 40
        },
        {
          "id": "attendance",
          "nameAr": "الحضور",
          "scorePct": 0.727,
          "maxPct": 10,
          "pct": 7.27
        },
        {
          "id": "uniform",
          "nameAr": "الزي الموحد",
          "scorePct": 0.636,
          "maxPct": 10,
          "pct": 6.36
        },
        {
          "id": "reflections",
          "nameAr": "الخواطر التربوية",
          "scorePct": 5,
          "maxPct": 5,
          "pct": 100
        },
        {
          "id": "mohsen",
          "nameAr": "وسام محسن",
          "scorePct": 4,
          "maxPct": 4,
          "pct": 100
        },
        {
          "id": "mubakkirun",
          "nameAr": "فقرة مبكرون",
          "scorePct": 1,
          "maxPct": 4,
          "pct": 25
        },
        {
          "id": "workshops",
          "nameAr": "الورش التدريبية",
          "scorePct": 3,
          "maxPct": 3,
          "pct": 100
        },
        {
          "id": "media",
          "nameAr": "الظهور الإعلامي",
          "scorePct": 1,
          "maxPct": 2,
          "pct": 50
        },
        {
          "id": "groupPhoto",
          "nameAr": "الصورة الجماعية",
          "scorePct": 2,
          "maxPct": 2,
          "pct": 100
        }
      ],
      "components": [
        {
          "id": "league",
          "nameAr": "الدوري التنافسي",
          "scorePct": 11.333,
          "maxPct": 30,
          "pct": 37.777
        },
        {
          "id": "project",
          "nameAr": "المشروع المجتمعي",
          "scorePct": 0,
          "maxPct": 20,
          "pct": 0
        },
        {
          "id": "haraki",
          "nameAr": "البرنامج الحركي",
          "scorePct": 4,
          "maxPct": 10,
          "pct": 40
        },
        {
          "id": "uniform",
          "nameAr": "الزي الموحد",
          "scorePct": 0.636,
          "maxPct": 10,
          "pct": 6.36
        },
        {
          "id": "attendance",
          "nameAr": "الحضور",
          "scorePct": 0.727,
          "maxPct": 10,
          "pct": 7.27
        },
        {
          "id": "educational",
          "nameAr": "الخواطر والورش",
          "scorePct": 8,
          "maxPct": 8,
          "pct": 100
        },
        {
          "id": "mohsen",
          "nameAr": "وسام محسن",
          "scorePct": 4,
          "maxPct": 4,
          "pct": 100
        },
        {
          "id": "mubakkirun",
          "nameAr": "فقرة مبكرون",
          "scorePct": 1,
          "maxPct": 4,
          "pct": 25
        },
        {
          "id": "mediaPhoto",
          "nameAr": "الإعلام والصورة",
          "scorePct": 3,
          "maxPct": 4,
          "pct": 75
        }
      ]
    },
    {
      "id": "G04",
      "index": 3,
      "nameAr": "علي بن ابي طالب",
      "captain": "احمد شميس",
      "deputy": "النائب 4",
      "members": 11,
      "rank": 2,
      "totalPct": 37.312,
      "medal": 2,
      "movement": null,
      "categories": [
        {
          "id": "football",
          "nameAr": "كرة القدم",
          "scorePct": 8.333,
          "maxPct": 10,
          "pct": 83.33
        },
        {
          "id": "volleyball",
          "nameAr": "كرة الطائرة",
          "scorePct": 8.333,
          "maxPct": 10,
          "pct": 83.33
        },
        {
          "id": "cultural",
          "nameAr": "المسابقة الثقافية",
          "scorePct": 2,
          "maxPct": 10,
          "pct": 20
        },
        {
          "id": "community",
          "nameAr": "اترك أثراً",
          "scorePct": 0,
          "maxPct": 20,
          "pct": 0
        },
        {
          "id": "haraki",
          "nameAr": "البرنامج الحركي",
          "scorePct": 3.5,
          "maxPct": 10,
          "pct": 35
        },
        {
          "id": "attendance",
          "nameAr": "الحضور",
          "scorePct": 0.727,
          "maxPct": 10,
          "pct": 7.27
        },
        {
          "id": "uniform",
          "nameAr": "الزي الموحد",
          "scorePct": 0.818,
          "maxPct": 10,
          "pct": 8.18
        },
        {
          "id": "reflections",
          "nameAr": "الخواطر التربوية",
          "scorePct": 3.5,
          "maxPct": 5,
          "pct": 70
        },
        {
          "id": "mohsen",
          "nameAr": "وسام محسن",
          "scorePct": 3,
          "maxPct": 4,
          "pct": 75
        },
        {
          "id": "mubakkirun",
          "nameAr": "فقرة مبكرون",
          "scorePct": 1,
          "maxPct": 4,
          "pct": 25
        },
        {
          "id": "workshops",
          "nameAr": "الورش التدريبية",
          "scorePct": 2.1,
          "maxPct": 3,
          "pct": 70
        },
        {
          "id": "media",
          "nameAr": "الظهور الإعلامي",
          "scorePct": 2,
          "maxPct": 2,
          "pct": 100
        },
        {
          "id": "groupPhoto",
          "nameAr": "الصورة الجماعية",
          "scorePct": 2,
          "maxPct": 2,
          "pct": 100
        }
      ],
      "components": [
        {
          "id": "league",
          "nameAr": "الدوري التنافسي",
          "scorePct": 18.667,
          "maxPct": 30,
          "pct": 62.223
        },
        {
          "id": "project",
          "nameAr": "المشروع المجتمعي",
          "scorePct": 0,
          "maxPct": 20,
          "pct": 0
        },
        {
          "id": "haraki",
          "nameAr": "البرنامج الحركي",
          "scorePct": 3.5,
          "maxPct": 10,
          "pct": 35
        },
        {
          "id": "uniform",
          "nameAr": "الزي الموحد",
          "scorePct": 0.818,
          "maxPct": 10,
          "pct": 8.18
        },
        {
          "id": "attendance",
          "nameAr": "الحضور",
          "scorePct": 0.727,
          "maxPct": 10,
          "pct": 7.27
        },
        {
          "id": "educational",
          "nameAr": "الخواطر والورش",
          "scorePct": 5.6,
          "maxPct": 8,
          "pct": 70
        },
        {
          "id": "mohsen",
          "nameAr": "وسام محسن",
          "scorePct": 3,
          "maxPct": 4,
          "pct": 75
        },
        {
          "id": "mubakkirun",
          "nameAr": "فقرة مبكرون",
          "scorePct": 1,
          "maxPct": 4,
          "pct": 25
        },
        {
          "id": "mediaPhoto",
          "nameAr": "الإعلام والصورة",
          "scorePct": 4,
          "maxPct": 4,
          "pct": 100
        }
      ]
    },
    {
      "id": "G05",
      "index": 4,
      "nameAr": "طلحة بن عبيد الله",
      "captain": "عبدالرحمن العبدالجادر",
      "deputy": "النائب 5",
      "members": 11,
      "rank": 3,
      "totalPct": 37.236,
      "medal": 3,
      "movement": null,
      "categories": [
        {
          "id": "football",
          "nameAr": "كرة القدم",
          "scorePct": 10,
          "maxPct": 10,
          "pct": 100
        },
        {
          "id": "volleyball",
          "nameAr": "كرة الطائرة",
          "scorePct": 10,
          "maxPct": 10,
          "pct": 100
        },
        {
          "id": "cultural",
          "nameAr": "المسابقة الثقافية",
          "scorePct": 0,
          "maxPct": 10,
          "pct": 0
        },
        {
          "id": "community",
          "nameAr": "اترك أثراً",
          "scorePct": 0,
          "maxPct": 20,
          "pct": 0
        },
        {
          "id": "haraki",
          "nameAr": "البرنامج الحركي",
          "scorePct": 3,
          "maxPct": 10,
          "pct": 30
        },
        {
          "id": "attendance",
          "nameAr": "الحضور",
          "scorePct": 0.727,
          "maxPct": 10,
          "pct": 7.27
        },
        {
          "id": "uniform",
          "nameAr": "الزي الموحد",
          "scorePct": 0.909,
          "maxPct": 10,
          "pct": 9.09
        },
        {
          "id": "reflections",
          "nameAr": "الخواطر التربوية",
          "scorePct": 3.5,
          "maxPct": 5,
          "pct": 70
        },
        {
          "id": "mohsen",
          "nameAr": "وسام محسن",
          "scorePct": 3,
          "maxPct": 4,
          "pct": 75
        },
        {
          "id": "mubakkirun",
          "nameAr": "فقرة مبكرون",
          "scorePct": 0,
          "maxPct": 4,
          "pct": 0
        },
        {
          "id": "workshops",
          "nameAr": "الورش التدريبية",
          "scorePct": 2.1,
          "maxPct": 3,
          "pct": 70
        },
        {
          "id": "media",
          "nameAr": "الظهور الإعلامي",
          "scorePct": 2,
          "maxPct": 2,
          "pct": 100
        },
        {
          "id": "groupPhoto",
          "nameAr": "الصورة الجماعية",
          "scorePct": 2,
          "maxPct": 2,
          "pct": 100
        }
      ],
      "components": [
        {
          "id": "league",
          "nameAr": "الدوري التنافسي",
          "scorePct": 20,
          "maxPct": 30,
          "pct": 66.667
        },
        {
          "id": "project",
          "nameAr": "المشروع المجتمعي",
          "scorePct": 0,
          "maxPct": 20,
          "pct": 0
        },
        {
          "id": "haraki",
          "nameAr": "البرنامج الحركي",
          "scorePct": 3,
          "maxPct": 10,
          "pct": 30
        },
        {
          "id": "uniform",
          "nameAr": "الزي الموحد",
          "scorePct": 0.909,
          "maxPct": 10,
          "pct": 9.09
        },
        {
          "id": "attendance",
          "nameAr": "الحضور",
          "scorePct": 0.727,
          "maxPct": 10,
          "pct": 7.27
        },
        {
          "id": "educational",
          "nameAr": "الخواطر والورش",
          "scorePct": 5.6,
          "maxPct": 8,
          "pct": 70
        },
        {
          "id": "mohsen",
          "nameAr": "وسام محسن",
          "scorePct": 3,
          "maxPct": 4,
          "pct": 75
        },
        {
          "id": "mubakkirun",
          "nameAr": "فقرة مبكرون",
          "scorePct": 0,
          "maxPct": 4,
          "pct": 0
        },
        {
          "id": "mediaPhoto",
          "nameAr": "الإعلام والصورة",
          "scorePct": 4,
          "maxPct": 4,
          "pct": 100
        }
      ]
    },
    {
      "id": "G06",
      "index": 5,
      "nameAr": "الزبير بن العوام",
      "captain": "قتيبة الحبشي",
      "deputy": "النائب 6",
      "members": 11,
      "rank": 5,
      "totalPct": 26.827,
      "medal": null,
      "movement": null,
      "categories": [
        {
          "id": "football",
          "nameAr": "كرة القدم",
          "scorePct": 5,
          "maxPct": 10,
          "pct": 50
        },
        {
          "id": "volleyball",
          "nameAr": "كرة الطائرة",
          "scorePct": 5,
          "maxPct": 10,
          "pct": 50
        },
        {
          "id": "cultural",
          "nameAr": "المسابقة الثقافية",
          "scorePct": 0,
          "maxPct": 10,
          "pct": 0
        },
        {
          "id": "community",
          "nameAr": "اترك أثراً",
          "scorePct": 0,
          "maxPct": 20,
          "pct": 0
        },
        {
          "id": "haraki",
          "nameAr": "البرنامج الحركي",
          "scorePct": 2.5,
          "maxPct": 10,
          "pct": 25
        },
        {
          "id": "attendance",
          "nameAr": "الحضور",
          "scorePct": 0.727,
          "maxPct": 10,
          "pct": 7.27
        },
        {
          "id": "uniform",
          "nameAr": "الزي الموحد",
          "scorePct": 1,
          "maxPct": 10,
          "pct": 10
        },
        {
          "id": "reflections",
          "nameAr": "الخواطر التربوية",
          "scorePct": 3.5,
          "maxPct": 5,
          "pct": 70
        },
        {
          "id": "mohsen",
          "nameAr": "وسام محسن",
          "scorePct": 3,
          "maxPct": 4,
          "pct": 75
        },
        {
          "id": "mubakkirun",
          "nameAr": "فقرة مبكرون",
          "scorePct": 0,
          "maxPct": 4,
          "pct": 0
        },
        {
          "id": "workshops",
          "nameAr": "الورش التدريبية",
          "scorePct": 2.1,
          "maxPct": 3,
          "pct": 70
        },
        {
          "id": "media",
          "nameAr": "الظهور الإعلامي",
          "scorePct": 2,
          "maxPct": 2,
          "pct": 100
        },
        {
          "id": "groupPhoto",
          "nameAr": "الصورة الجماعية",
          "scorePct": 2,
          "maxPct": 2,
          "pct": 100
        }
      ],
      "components": [
        {
          "id": "league",
          "nameAr": "الدوري التنافسي",
          "scorePct": 10,
          "maxPct": 30,
          "pct": 33.333
        },
        {
          "id": "project",
          "nameAr": "المشروع المجتمعي",
          "scorePct": 0,
          "maxPct": 20,
          "pct": 0
        },
        {
          "id": "haraki",
          "nameAr": "البرنامج الحركي",
          "scorePct": 2.5,
          "maxPct": 10,
          "pct": 25
        },
        {
          "id": "uniform",
          "nameAr": "الزي الموحد",
          "scorePct": 1,
          "maxPct": 10,
          "pct": 10
        },
        {
          "id": "attendance",
          "nameAr": "الحضور",
          "scorePct": 0.727,
          "maxPct": 10,
          "pct": 7.27
        },
        {
          "id": "educational",
          "nameAr": "الخواطر والورش",
          "scorePct": 5.6,
          "maxPct": 8,
          "pct": 70
        },
        {
          "id": "mohsen",
          "nameAr": "وسام محسن",
          "scorePct": 3,
          "maxPct": 4,
          "pct": 75
        },
        {
          "id": "mubakkirun",
          "nameAr": "فقرة مبكرون",
          "scorePct": 0,
          "maxPct": 4,
          "pct": 0
        },
        {
          "id": "mediaPhoto",
          "nameAr": "الإعلام والصورة",
          "scorePct": 4,
          "maxPct": 4,
          "pct": 100
        }
      ]
    },
    {
      "id": "G07",
      "index": 6,
      "nameAr": "سعد بن ابي وقاص",
      "captain": "يوسف الطواله",
      "deputy": "النائب 7",
      "members": 11,
      "rank": 8,
      "totalPct": 17.842,
      "medal": null,
      "movement": null,
      "categories": [
        {
          "id": "football",
          "nameAr": "كرة القدم",
          "scorePct": 1.667,
          "maxPct": 10,
          "pct": 16.67
        },
        {
          "id": "volleyball",
          "nameAr": "كرة الطائرة",
          "scorePct": 1.667,
          "maxPct": 10,
          "pct": 16.67
        },
        {
          "id": "cultural",
          "nameAr": "المسابقة الثقافية",
          "scorePct": 0,
          "maxPct": 10,
          "pct": 0
        },
        {
          "id": "community",
          "nameAr": "اترك أثراً",
          "scorePct": 0,
          "maxPct": 20,
          "pct": 0
        },
        {
          "id": "haraki",
          "nameAr": "البرنامج الحركي",
          "scorePct": 2,
          "maxPct": 10,
          "pct": 20
        },
        {
          "id": "attendance",
          "nameAr": "الحضور",
          "scorePct": 0.727,
          "maxPct": 10,
          "pct": 7.27
        },
        {
          "id": "uniform",
          "nameAr": "الزي الموحد",
          "scorePct": 0.182,
          "maxPct": 10,
          "pct": 1.82
        },
        {
          "id": "reflections",
          "nameAr": "الخواطر التربوية",
          "scorePct": 3.5,
          "maxPct": 5,
          "pct": 70
        },
        {
          "id": "mohsen",
          "nameAr": "وسام محسن",
          "scorePct": 3,
          "maxPct": 4,
          "pct": 75
        },
        {
          "id": "mubakkirun",
          "nameAr": "فقرة مبكرون",
          "scorePct": 0,
          "maxPct": 4,
          "pct": 0
        },
        {
          "id": "workshops",
          "nameAr": "الورش التدريبية",
          "scorePct": 2.1,
          "maxPct": 3,
          "pct": 70
        },
        {
          "id": "media",
          "nameAr": "الظهور الإعلامي",
          "scorePct": 1,
          "maxPct": 2,
          "pct": 50
        },
        {
          "id": "groupPhoto",
          "nameAr": "الصورة الجماعية",
          "scorePct": 2,
          "maxPct": 2,
          "pct": 100
        }
      ],
      "components": [
        {
          "id": "league",
          "nameAr": "الدوري التنافسي",
          "scorePct": 3.333,
          "maxPct": 30,
          "pct": 11.11
        },
        {
          "id": "project",
          "nameAr": "المشروع المجتمعي",
          "scorePct": 0,
          "maxPct": 20,
          "pct": 0
        },
        {
          "id": "haraki",
          "nameAr": "البرنامج الحركي",
          "scorePct": 2,
          "maxPct": 10,
          "pct": 20
        },
        {
          "id": "uniform",
          "nameAr": "الزي الموحد",
          "scorePct": 0.182,
          "maxPct": 10,
          "pct": 1.82
        },
        {
          "id": "attendance",
          "nameAr": "الحضور",
          "scorePct": 0.727,
          "maxPct": 10,
          "pct": 7.27
        },
        {
          "id": "educational",
          "nameAr": "الخواطر والورش",
          "scorePct": 5.6,
          "maxPct": 8,
          "pct": 70
        },
        {
          "id": "mohsen",
          "nameAr": "وسام محسن",
          "scorePct": 3,
          "maxPct": 4,
          "pct": 75
        },
        {
          "id": "mubakkirun",
          "nameAr": "فقرة مبكرون",
          "scorePct": 0,
          "maxPct": 4,
          "pct": 0
        },
        {
          "id": "mediaPhoto",
          "nameAr": "الإعلام والصورة",
          "scorePct": 3,
          "maxPct": 4,
          "pct": 75
        }
      ]
    },
    {
      "id": "G08",
      "index": 7,
      "nameAr": "عبدالرحمن بن عوف",
      "captain": "احمد الحداد",
      "deputy": "النائب 8",
      "members": 11,
      "rank": 7,
      "totalPct": 20.858,
      "medal": null,
      "movement": null,
      "categories": [
        {
          "id": "football",
          "nameAr": "كرة القدم",
          "scorePct": 3.333,
          "maxPct": 10,
          "pct": 33.33
        },
        {
          "id": "volleyball",
          "nameAr": "كرة الطائرة",
          "scorePct": 3.333,
          "maxPct": 10,
          "pct": 33.33
        },
        {
          "id": "cultural",
          "nameAr": "المسابقة الثقافية",
          "scorePct": 0,
          "maxPct": 10,
          "pct": 0
        },
        {
          "id": "community",
          "nameAr": "اترك أثراً",
          "scorePct": 0,
          "maxPct": 20,
          "pct": 0
        },
        {
          "id": "haraki",
          "nameAr": "البرنامج الحركي",
          "scorePct": 1.5,
          "maxPct": 10,
          "pct": 15
        },
        {
          "id": "attendance",
          "nameAr": "الحضور",
          "scorePct": 0.727,
          "maxPct": 10,
          "pct": 7.27
        },
        {
          "id": "uniform",
          "nameAr": "الزي الموحد",
          "scorePct": 0.364,
          "maxPct": 10,
          "pct": 3.64
        },
        {
          "id": "reflections",
          "nameAr": "الخواطر التربوية",
          "scorePct": 3.5,
          "maxPct": 5,
          "pct": 70
        },
        {
          "id": "mohsen",
          "nameAr": "وسام محسن",
          "scorePct": 3,
          "maxPct": 4,
          "pct": 75
        },
        {
          "id": "mubakkirun",
          "nameAr": "فقرة مبكرون",
          "scorePct": 0,
          "maxPct": 4,
          "pct": 0
        },
        {
          "id": "workshops",
          "nameAr": "الورش التدريبية",
          "scorePct": 2.1,
          "maxPct": 3,
          "pct": 70
        },
        {
          "id": "media",
          "nameAr": "الظهور الإعلامي",
          "scorePct": 1,
          "maxPct": 2,
          "pct": 50
        },
        {
          "id": "groupPhoto",
          "nameAr": "الصورة الجماعية",
          "scorePct": 2,
          "maxPct": 2,
          "pct": 100
        }
      ],
      "components": [
        {
          "id": "league",
          "nameAr": "الدوري التنافسي",
          "scorePct": 6.667,
          "maxPct": 30,
          "pct": 22.223
        },
        {
          "id": "project",
          "nameAr": "المشروع المجتمعي",
          "scorePct": 0,
          "maxPct": 20,
          "pct": 0
        },
        {
          "id": "haraki",
          "nameAr": "البرنامج الحركي",
          "scorePct": 1.5,
          "maxPct": 10,
          "pct": 15
        },
        {
          "id": "uniform",
          "nameAr": "الزي الموحد",
          "scorePct": 0.364,
          "maxPct": 10,
          "pct": 3.64
        },
        {
          "id": "attendance",
          "nameAr": "الحضور",
          "scorePct": 0.727,
          "maxPct": 10,
          "pct": 7.27
        },
        {
          "id": "educational",
          "nameAr": "الخواطر والورش",
          "scorePct": 5.6,
          "maxPct": 8,
          "pct": 70
        },
        {
          "id": "mohsen",
          "nameAr": "وسام محسن",
          "scorePct": 3,
          "maxPct": 4,
          "pct": 75
        },
        {
          "id": "mubakkirun",
          "nameAr": "فقرة مبكرون",
          "scorePct": 0,
          "maxPct": 4,
          "pct": 0
        },
        {
          "id": "mediaPhoto",
          "nameAr": "الإعلام والصورة",
          "scorePct": 3,
          "maxPct": 4,
          "pct": 75
        }
      ]
    }
  ],
  "ranking": [
    {
      "rank": 1,
      "groupId": "G01",
      "nameAr": "أبو بكر الصديق",
      "totalPct": 54.236,
      "movement": null,
      "medal": 1
    },
    {
      "rank": 2,
      "groupId": "G04",
      "nameAr": "علي بن ابي طالب",
      "totalPct": 37.312,
      "movement": null,
      "medal": 2
    },
    {
      "rank": 3,
      "groupId": "G05",
      "nameAr": "طلحة بن عبيد الله",
      "totalPct": 37.236,
      "movement": null,
      "medal": 3
    },
    {
      "rank": 4,
      "groupId": "G03",
      "nameAr": "عثمان بن عفان",
      "totalPct": 32.697,
      "movement": null,
      "medal": null
    },
    {
      "rank": 5,
      "groupId": "G06",
      "nameAr": "الزبير بن العوام",
      "totalPct": 26.827,
      "movement": null,
      "medal": null
    },
    {
      "rank": 6,
      "groupId": "G02",
      "nameAr": "عمر بن الخطاب",
      "totalPct": 25.6,
      "movement": null,
      "medal": null
    },
    {
      "rank": 7,
      "groupId": "G08",
      "nameAr": "عبدالرحمن بن عوف",
      "totalPct": 20.858,
      "movement": null,
      "medal": null
    },
    {
      "rank": 8,
      "groupId": "G07",
      "nameAr": "سعد بن ابي وقاص",
      "totalPct": 17.842,
      "movement": null,
      "medal": null
    }
  ],
  "competitions": {
    "football": {
      "nameAr": "كرة القدم",
      "weightPct": 10,
      "roundsCount": 4,
      "roundScorePct": 2.5,
      "win": 3,
      "draw": 1,
      "loss": 0,
      "perGroup": [
        {
          "groupId": "G01",
          "rounds": [
            {
              "w": 2,
              "d": 1,
              "l": 1,
              "points": 7,
              "maxPoints": 12,
              "pct": 58.333,
              "scorePct": 1.458
            },
            {
              "w": 2,
              "d": 1,
              "l": 1,
              "points": 7,
              "maxPoints": 12,
              "pct": 58.333,
              "scorePct": 1.458
            },
            {
              "w": 2,
              "d": 1,
              "l": 1,
              "points": 7,
              "maxPoints": 12,
              "pct": 58.333,
              "scorePct": 1.458
            },
            {
              "w": 2,
              "d": 1,
              "l": 1,
              "points": 7,
              "maxPoints": 12,
              "pct": 58.333,
              "scorePct": 1.458
            }
          ],
          "totalPoints": 48,
          "maxPoints": 48,
          "pct": 100,
          "scorePct": 10,
          "rankInComp": 1
        },
        {
          "groupId": "G02",
          "rounds": [
            {
              "w": 0,
              "d": 2,
              "l": 2,
              "points": 2,
              "maxPoints": 12,
              "pct": 16.667,
              "scorePct": 0.417
            },
            {
              "w": 0,
              "d": 2,
              "l": 2,
              "points": 2,
              "maxPoints": 12,
              "pct": 16.667,
              "scorePct": 0.417
            },
            {
              "w": 0,
              "d": 2,
              "l": 2,
              "points": 2,
              "maxPoints": 12,
              "pct": 16.667,
              "scorePct": 0.417
            },
            {
              "w": 0,
              "d": 2,
              "l": 2,
              "points": 2,
              "maxPoints": 12,
              "pct": 16.667,
              "scorePct": 0.417
            }
          ],
          "totalPoints": 8,
          "maxPoints": 48,
          "pct": 16.667,
          "scorePct": 1.667,
          "rankInComp": 7
        },
        {
          "groupId": "G03",
          "rounds": [
            {
              "w": 1,
              "d": 2,
              "l": 1,
              "points": 5,
              "maxPoints": 12,
              "pct": 41.667,
              "scorePct": 1.042
            },
            {
              "w": 1,
              "d": 2,
              "l": 1,
              "points": 5,
              "maxPoints": 12,
              "pct": 41.667,
              "scorePct": 1.042
            },
            {
              "w": 1,
              "d": 2,
              "l": 1,
              "points": 5,
              "maxPoints": 12,
              "pct": 41.667,
              "scorePct": 1.042
            },
            {
              "w": 1,
              "d": 2,
              "l": 1,
              "points": 5,
              "maxPoints": 12,
              "pct": 41.667,
              "scorePct": 1.042
            }
          ],
          "totalPoints": 20,
          "maxPoints": 48,
          "pct": 41.667,
          "scorePct": 4.167,
          "rankInComp": 5
        },
        {
          "groupId": "G04",
          "rounds": [
            {
              "w": 3,
              "d": 1,
              "l": 0,
              "points": 10,
              "maxPoints": 12,
              "pct": 83.333,
              "scorePct": 2.083
            },
            {
              "w": 3,
              "d": 1,
              "l": 0,
              "points": 10,
              "maxPoints": 12,
              "pct": 83.333,
              "scorePct": 2.083
            },
            {
              "w": 3,
              "d": 1,
              "l": 0,
              "points": 10,
              "maxPoints": 12,
              "pct": 83.333,
              "scorePct": 2.083
            },
            {
              "w": 3,
              "d": 1,
              "l": 0,
              "points": 10,
              "maxPoints": 12,
              "pct": 83.333,
              "scorePct": 2.083
            }
          ],
          "totalPoints": 40,
          "maxPoints": 48,
          "pct": 83.333,
          "scorePct": 8.333,
          "rankInComp": 3
        },
        {
          "groupId": "G05",
          "rounds": [
            {
              "w": 4,
              "d": 0,
              "l": 0,
              "points": 12,
              "maxPoints": 12,
              "pct": 100,
              "scorePct": 2.5
            },
            {
              "w": 4,
              "d": 0,
              "l": 0,
              "points": 12,
              "maxPoints": 12,
              "pct": 100,
              "scorePct": 2.5
            },
            {
              "w": 4,
              "d": 0,
              "l": 0,
              "points": 12,
              "maxPoints": 12,
              "pct": 100,
              "scorePct": 2.5
            },
            {
              "w": 4,
              "d": 0,
              "l": 0,
              "points": 12,
              "maxPoints": 12,
              "pct": 100,
              "scorePct": 2.5
            }
          ],
          "totalPoints": 48,
          "maxPoints": 48,
          "pct": 100,
          "scorePct": 10,
          "rankInComp": 1
        },
        {
          "groupId": "G06",
          "rounds": [
            {
              "w": 1,
              "d": 3,
              "l": 0,
              "points": 6,
              "maxPoints": 12,
              "pct": 50,
              "scorePct": 1.25
            },
            {
              "w": 1,
              "d": 3,
              "l": 0,
              "points": 6,
              "maxPoints": 12,
              "pct": 50,
              "scorePct": 1.25
            },
            {
              "w": 1,
              "d": 3,
              "l": 0,
              "points": 6,
              "maxPoints": 12,
              "pct": 50,
              "scorePct": 1.25
            },
            {
              "w": 1,
              "d": 3,
              "l": 0,
              "points": 6,
              "maxPoints": 12,
              "pct": 50,
              "scorePct": 1.25
            }
          ],
          "totalPoints": 24,
          "maxPoints": 48,
          "pct": 50,
          "scorePct": 5,
          "rankInComp": 4
        },
        {
          "groupId": "G07",
          "rounds": [
            {
              "w": 0,
              "d": 2,
              "l": 2,
              "points": 2,
              "maxPoints": 12,
              "pct": 16.667,
              "scorePct": 0.417
            },
            {
              "w": 0,
              "d": 2,
              "l": 2,
              "points": 2,
              "maxPoints": 12,
              "pct": 16.667,
              "scorePct": 0.417
            },
            {
              "w": 0,
              "d": 2,
              "l": 2,
              "points": 2,
              "maxPoints": 12,
              "pct": 16.667,
              "scorePct": 0.417
            },
            {
              "w": 0,
              "d": 2,
              "l": 2,
              "points": 2,
              "maxPoints": 12,
              "pct": 16.667,
              "scorePct": 0.417
            }
          ],
          "totalPoints": 8,
          "maxPoints": 48,
          "pct": 16.667,
          "scorePct": 1.667,
          "rankInComp": 7
        },
        {
          "groupId": "G08",
          "rounds": [
            {
              "w": 1,
              "d": 1,
              "l": 2,
              "points": 4,
              "maxPoints": 12,
              "pct": 33.333,
              "scorePct": 0.833
            },
            {
              "w": 1,
              "d": 1,
              "l": 2,
              "points": 4,
              "maxPoints": 12,
              "pct": 33.333,
              "scorePct": 0.833
            },
            {
              "w": 1,
              "d": 1,
              "l": 2,
              "points": 4,
              "maxPoints": 12,
              "pct": 33.333,
              "scorePct": 0.833
            },
            {
              "w": 1,
              "d": 1,
              "l": 2,
              "points": 4,
              "maxPoints": 12,
              "pct": 33.333,
              "scorePct": 0.833
            }
          ],
          "totalPoints": 16,
          "maxPoints": 48,
          "pct": 33.333,
          "scorePct": 3.333,
          "rankInComp": 6
        }
      ]
    },
    "volleyball": {
      "nameAr": "كرة الطائرة",
      "weightPct": 10,
      "roundsCount": 2,
      "roundScorePct": 5,
      "win": 3,
      "draw": 1,
      "loss": 0,
      "perGroup": [
        {
          "groupId": "G01",
          "round1": {
            "w": 2,
            "d": 1,
            "l": 1,
            "points": 7
          },
          "round2Points": 11,
          "totalPoints": 18,
          "maxPoints": 12,
          "pct": 150,
          "scorePct": 15,
          "rankInComp": 1
        },
        {
          "groupId": "G02",
          "round1": {
            "w": 0,
            "d": 2,
            "l": 2,
            "points": 2
          },
          "round2Points": 0,
          "totalPoints": 2,
          "maxPoints": 12,
          "pct": 16.667,
          "scorePct": 1.667,
          "rankInComp": 7
        },
        {
          "groupId": "G03",
          "round1": {
            "w": 1,
            "d": 2,
            "l": 1,
            "points": 5
          },
          "round2Points": 0,
          "totalPoints": 5,
          "maxPoints": 12,
          "pct": 41.667,
          "scorePct": 4.167,
          "rankInComp": 5
        },
        {
          "groupId": "G04",
          "round1": {
            "w": 3,
            "d": 1,
            "l": 0,
            "points": 10
          },
          "round2Points": 0,
          "totalPoints": 10,
          "maxPoints": 12,
          "pct": 83.333,
          "scorePct": 8.333,
          "rankInComp": 3
        },
        {
          "groupId": "G05",
          "round1": {
            "w": 4,
            "d": 0,
            "l": 0,
            "points": 12
          },
          "round2Points": 0,
          "totalPoints": 12,
          "maxPoints": 12,
          "pct": 100,
          "scorePct": 10,
          "rankInComp": 2
        },
        {
          "groupId": "G06",
          "round1": {
            "w": 1,
            "d": 3,
            "l": 0,
            "points": 6
          },
          "round2Points": 0,
          "totalPoints": 6,
          "maxPoints": 12,
          "pct": 50,
          "scorePct": 5,
          "rankInComp": 4
        },
        {
          "groupId": "G07",
          "round1": {
            "w": 0,
            "d": 2,
            "l": 2,
            "points": 2
          },
          "round2Points": 0,
          "totalPoints": 2,
          "maxPoints": 12,
          "pct": 16.667,
          "scorePct": 1.667,
          "rankInComp": 7
        },
        {
          "groupId": "G08",
          "round1": {
            "w": 1,
            "d": 1,
            "l": 2,
            "points": 4
          },
          "round2Points": 0,
          "totalPoints": 4,
          "maxPoints": 12,
          "pct": 33.333,
          "scorePct": 3.333,
          "rankInComp": 6
        }
      ]
    },
    "cultural": {
      "nameAr": "المسابقة الثقافية",
      "weightPct": 10,
      "contestsCount": 2,
      "contestScorePct": 5,
      "placePoints": [
        5,
        4,
        3,
        2
      ],
      "perGroup": [
        {
          "groupId": "G01",
          "contests": [
            {
              "position": 1,
              "points": 5
            },
            {
              "position": 2,
              "points": 4
            }
          ],
          "totalPoints": 9,
          "scorePct": 9,
          "rankInComp": 1
        },
        {
          "groupId": "G02",
          "contests": [
            {
              "position": 2,
              "points": 4
            },
            {
              "position": 0,
              "points": 0
            }
          ],
          "totalPoints": 4,
          "scorePct": 4,
          "rankInComp": 2
        },
        {
          "groupId": "G03",
          "contests": [
            {
              "position": 3,
              "points": 3
            },
            {
              "position": 0,
              "points": 0
            }
          ],
          "totalPoints": 3,
          "scorePct": 3,
          "rankInComp": 3
        },
        {
          "groupId": "G04",
          "contests": [
            {
              "position": 4,
              "points": 2
            },
            {
              "position": 0,
              "points": 0
            }
          ],
          "totalPoints": 2,
          "scorePct": 2,
          "rankInComp": 4
        },
        {
          "groupId": "G05",
          "contests": [
            {
              "position": 5,
              "points": 0
            },
            {
              "position": 0,
              "points": 0
            }
          ],
          "totalPoints": 0,
          "scorePct": 0,
          "rankInComp": 5
        },
        {
          "groupId": "G06",
          "contests": [
            {
              "position": 6,
              "points": 0
            },
            {
              "position": 0,
              "points": 0
            }
          ],
          "totalPoints": 0,
          "scorePct": 0,
          "rankInComp": 5
        },
        {
          "groupId": "G07",
          "contests": [
            {
              "position": 7,
              "points": 0
            },
            {
              "position": 0,
              "points": 0
            }
          ],
          "totalPoints": 0,
          "scorePct": 0,
          "rankInComp": 5
        },
        {
          "groupId": "G08",
          "contests": [
            {
              "position": 8,
              "points": 0
            },
            {
              "position": 0,
              "points": 0
            }
          ],
          "totalPoints": 0,
          "scorePct": 0,
          "rankInComp": 5
        }
      ]
    },
    "leagueSummary": [
      {
        "groupId": "G01",
        "footballPct": 10,
        "volleyballPct": 15,
        "culturalPct": 9,
        "totalPct": 34,
        "rank": 1
      },
      {
        "groupId": "G02",
        "footballPct": 1.667,
        "volleyballPct": 1.667,
        "culturalPct": 4,
        "totalPct": 7.333,
        "rank": 6
      },
      {
        "groupId": "G03",
        "footballPct": 4.167,
        "volleyballPct": 4.167,
        "culturalPct": 3,
        "totalPct": 11.333,
        "rank": 4
      },
      {
        "groupId": "G04",
        "footballPct": 8.333,
        "volleyballPct": 8.333,
        "culturalPct": 2,
        "totalPct": 18.667,
        "rank": 3
      },
      {
        "groupId": "G05",
        "footballPct": 10,
        "volleyballPct": 10,
        "culturalPct": 0,
        "totalPct": 20,
        "rank": 2
      },
      {
        "groupId": "G06",
        "footballPct": 5,
        "volleyballPct": 5,
        "culturalPct": 0,
        "totalPct": 10,
        "rank": 5
      },
      {
        "groupId": "G07",
        "footballPct": 1.667,
        "volleyballPct": 1.667,
        "culturalPct": 0,
        "totalPct": 3.333,
        "rank": 8
      },
      {
        "groupId": "G08",
        "footballPct": 3.333,
        "volleyballPct": 3.333,
        "culturalPct": 0,
        "totalPct": 6.667,
        "rank": 7
      }
    ]
  },
  "awards": [
    {
      "id": "bestAttendance",
      "titleAr": "أفضل حضور",
      "groupId": "G01",
      "detail": "9.1%"
    },
    {
      "id": "bestProject",
      "titleAr": "أفضل مشروع",
      "groupId": "G01"
    },
    {
      "id": "bestCultural",
      "titleAr": "أفضل ثقافي",
      "groupId": "G01",
      "detail": "90%"
    },
    {
      "id": "bestSports",
      "titleAr": "أفضل رياضي",
      "groupId": "G01"
    },
    {
      "id": "bestMohsen",
      "titleAr": "أفضل محسن",
      "groupId": "G01"
    },
    {
      "id": "bestMedia",
      "titleAr": "أفضل إعلام",
      "groupId": "G04",
      "detail": "100%"
    },
    {
      "id": "bestReflection",
      "titleAr": "أفضل خواطر تربوية",
      "groupId": "G03",
      "detail": "100%"
    },
    {
      "id": "bestWorkshop",
      "titleAr": "أفضل ورش تدريبية",
      "groupId": "G03",
      "detail": "100%"
    }
  ],
  "stats": {
    "highestPct": 54.236,
    "averagePct": 31.576,
    "lowestPct": 17.842,
    "leaderGroupId": "G01",
    "groupsCount": 8,
    "categoriesCount": 13
  },
  "history": [
    {
      "syncedAt": "2026-07-19T21:23:25Z",
      "entries": [
        {
          "groupId": "G01",
          "rank": 1,
          "totalPct": 54.236
        },
        {
          "groupId": "G02",
          "rank": 6,
          "totalPct": 25.6
        },
        {
          "groupId": "G03",
          "rank": 4,
          "totalPct": 32.697
        },
        {
          "groupId": "G04",
          "rank": 2,
          "totalPct": 37.312
        },
        {
          "groupId": "G05",
          "rank": 3,
          "totalPct": 37.236
        },
        {
          "groupId": "G06",
          "rank": 5,
          "totalPct": 26.827
        },
        {
          "groupId": "G07",
          "rank": 8,
          "totalPct": 17.842
        },
        {
          "groupId": "G08",
          "rank": 7,
          "totalPct": 20.858
        }
      ]
    }
  ]
}